xenon_view_sdk/__init__.py
xenon_view_sdk/xenon-view-sdk-deanonymize_test.py
xenon_view_sdk/xenon-view-sdk-heartbeat_test.py
xenon_view_sdk/xenon-view-sdk-journey_test.py
xenon_view_sdk/xenon-view-sdk_test.py
xenon_view_sdk-0.1.10.dist-info/METADATA
xenon_view_sdk-0.1.10.dist-info/WHEEL
xenon_view_sdk-0.1.10.dist-info/top_level.txt
xenon_view_sdk-0.1.10.dist-info/RECORD
