Metadata-Version: 2.1
Name: xenon-view-sdk
Version: 0.1.10
Summary: Python access to Xenon View.
Home-page: https://github.com/xenonview-com/view-python-sdk
Maintainer: Luke Woydziak
Maintainer-email: lwoydziak@gmail.com
License: UNKNOWN
Download-URL: https://github.com/xenonview-com/view-python-sdk/tarball/1.0
Platform: any
Classifier: Development Status :: 4 - Beta
Classifier: Natural Language :: English
Classifier: Operating System :: Unix
Classifier: Programming Language :: Python
Classifier: Programming Language :: Unix Shell
Classifier: Topic :: Software Development :: Libraries :: Python Modules
Requires-Python: >=3
Requires-Dist: singleton3
Requires-Dist: requests
Requires-Dist: pytz
